elr_lrt/model.py
elr_lrt/__init__.py
elr_lrt/dbpm.cpython-310-x86_64-linux-gnu.so
elr_lrt-0.1.6.dist-info/WHEEL
elr_lrt-0.1.6.dist-info/RECORD
elr_lrt-0.1.6.dist-info/top_level.txt
elr_lrt-0.1.6.dist-info/METADATA
