Metadata-Version: 2.1
Name: elr-lrt
Version: 0.1.6
Summary: ELR LRT Python package
Author: Prabin Panta
Author-email: PrabinPanta0 <pantaprabin30@gmail.com>
Project-URL: Homepage, https://github.com/PrabinPanta0/elr-lrt
Project-URL: Bug Tracker, https://github.com/PrabinPanta0/elr-lrt/issues
Classifier: Programming Language :: Python :: 3
Classifier: License :: OSI Approved :: MIT License
Classifier: Operating System :: OS Independent
Requires-Python: >=3.7
Requires-Dist: pybind11>=2.6.0
